avid/__init__.py
avid/actions/__init__.py
avid/actions/actionBatchGenerator.py
avid/actions/artefactRefine.py
avid/actions/cliActionBase.py
avid/actions/cliBatchScheduler.py
avid/actions/dummy.py
avid/actions/genericCLIAction.py
avid/actions/pointSetConversion.py
avid/actions/pythonAction.py
avid/actions/regVarTool.py
avid/actions/simpleScheduler.py
avid/actions/testingScheduler.py
avid/actions/threadingScheduler.py
avid/actions/fitting/__init__.py
avid/actions/fitting/linearfit.py
avid/actions/matchpoint/__init__.py
avid/actions/matchpoint/combineR.py
avid/actions/matchpoint/mapR.py
avid/actions/matchpoint/matchR.py
avid/actions/mitk/MitkCLGlobalImageFeatures.py
avid/actions/mitk/MitkFileConverter.py
avid/actions/mitk/MitkFuse3Dto4DImage.py
avid/actions/mitk/MitkGIFeatureValueCollector.py
avid/actions/mitk/MitkMRPerfusion.py
avid/actions/mitk/MitkMRSignal2Concentration.py
avid/actions/mitk/MitkMapImage.py
avid/actions/mitk/MitkMatchImage.py
avid/actions/mitk/MitkResampleImage.py
avid/actions/mitk/MitkResampleMask.py
avid/actions/mitk/MitkSplit4Dto3DImages.py
avid/actions/mitk/MitkStitchImages.py
avid/actions/mitk/__init__.py
avid/actions/mitk/taskListGenerator.py
avid/actions/plastimatch/__init__.py
avid/actions/plastimatch/plmCompare.py
avid/actions/plastimatch/plmDice.py
avid/actions/plastimatch/plmRTSSMap.py
avid/actions/rttb/DoseTool.py
avid/actions/rttb/__init__.py
avid/actions/rttb/bioModelCalc.py
avid/actions/rttb/doseAcc.py
avid/actions/rttb/doseMap.py
avid/actions/rttb/doseStatsCollector.py
avid/actions/rttb/imageAcc.py
avid/actions/rttb/voxelizer.py
avid/actions/unrefactored/CurveDescriptorMiniApp.py
avid/actions/unrefactored/PixelDumpMiniApp.py
avid/actions/unrefactored/cleanWorkflow.py
avid/actions/unrefactored/invertR.py
avid/cli/__init__.py
avid/cli/avidconfig.py
avid/cli/aviddiag.py
avid/cli/avidsplit.py
avid/cli/tool-packages/MITK/sources.config
avid/cli/tool-packages/MITK/tools.config
avid/common/AVIDUrlLocater.py
avid/common/__init__.py
avid-0.0.1.dist-info/licenses/LICENSE
avid-0.0.1.dist-info/METADATA
avid-0.0.1.dist-info/WHEEL
avid-0.0.1.dist-info/entry_points.txt
avid-0.0.1.dist-info/top_level.txt
avid-0.0.1.dist-info/RECORD
