Metadata-Version: 2.4
Name: AVID
Version: 0.0.1
Summary: AVID is a Python framework for declarative, data-driven processing of large-scale image datasets, particularly designed for biomedical image analysis workflows.
Author-email: "MIC@DKFZ" <r.floca@dkfz-heidelberg.de>
License-Expression: Apache-2.0
Project-URL: Homepage, https://github.com/MIC-DKFZ/AVID
Project-URL: Documentation, https://avid.readthedocs.io/en/latest
Project-URL: Issues, https://github.com/MIC-DKFZ/AVID/issues
Project-URL: MITK, http://mitk.org
Classifier: Programming Language :: Python :: 3
Classifier: Operating System :: OS Independent
Requires-Python: >=3.8
License-File: LICENSE
Requires-Dist: toml==0.10.2
Requires-Dist: platformdirs==4.3.8
Provides-Extra: rich
Requires-Dist: rich==13.7.1; extra == "rich"
Provides-Extra: mac
Requires-Dist: dmglib==0.9.6; extra == "mac"
Provides-Extra: dev
Requires-Dist: black; extra == "dev"
Requires-Dist: isort; extra == "dev"
Requires-Dist: flake8; extra == "dev"
Dynamic: license-file
